yyperf/__init__.py
yyperf/__main__.py
yyperf/aapt-arm-pie
yyperf/page.xml
yyperf/static/favicon.ico
yyperf/static/loading.svg
yyperf/static/running.svg
yyperf/static/style.css
yyperf/static/ace/ace.js
yyperf/static/ace/ext-language_tools.js
yyperf/static/ace/keybinding-vim.js
yyperf/static/ace/mode-python.js
yyperf/static/ace/theme-monokai.js
yyperf/static/cdn_libraries/cdn.jsdelivr.net/bootstrap/3.3.7/css/bootstrap.min.css
yyperf/static/cdn_libraries/cdn.jsdelivr.net/bootstrap/3.3.7/css/bootstrap.min.css.map
yyperf/static/cdn_libraries/cdn.jsdelivr.net/bootstrap/3.3.7/fonts/glyphicons-halflings-regular.woff2
yyperf/static/cdn_libraries/cdn.jsdelivr.net/bootstrap/3.3.7/js/bootstrap.min.js
yyperf/static/cdn_libraries/cdn.jsdelivr.net/bootstrap.select/1.12.2/css/bootstrap-select.min.css
yyperf/static/cdn_libraries/cdn.jsdelivr.net/bootstrap.select/1.12.2/js/bootstrap-select.js.map
yyperf/static/cdn_libraries/cdn.jsdelivr.net/bootstrap.select/1.12.2/js/bootstrap-select.min.js
yyperf/static/cdn_libraries/cdn.jsdelivr.net/npm/vue-resource@1.5.1
yyperf/static/cdn_libraries/cdn.jsdelivr.net/npm/ace-builds@1.4.12/src-noconflict/ace.min.js
yyperf/static/cdn_libraries/cdn.jsdelivr.net/npm/ace-builds@1.4.12/src-noconflict/ext-language_tools.min.js
yyperf/static/cdn_libraries/cdn.jsdelivr.net/npm/ace-builds@1.4.12/src-noconflict/ext-searchbox.min.js
yyperf/static/cdn_libraries/cdn.jsdelivr.net/npm/ace-builds@1.4.12/src-noconflict/mode-python.min.js
yyperf/static/cdn_libraries/cdn.jsdelivr.net/npm/ace-builds@1.4.12/src-noconflict/theme-monokai.js
yyperf/static/cdn_libraries/cdn.jsdelivr.net/npm/echart@5.3.0/dist/echarts.common.js
yyperf/static/cdn_libraries/cdn.jsdelivr.net/npm/echart@5.3.0/dist/echarts.common.js.map
yyperf/static/cdn_libraries/cdn.jsdelivr.net/npm/echart@5.3.0/dist/echarts.common.min.js
yyperf/static/cdn_libraries/cdn.jsdelivr.net/npm/echart@5.3.0/dist/echarts.esm.js
yyperf/static/cdn_libraries/cdn.jsdelivr.net/npm/echart@5.3.0/dist/echarts.esm.js.map
yyperf-0.6.9.dist-info/AUTHORS
yyperf-0.6.9.dist-info/LICENSE
yyperf-0.6.9.dist-info/METADATA
yyperf-0.6.9.dist-info/WHEEL
yyperf-0.6.9.dist-info/entry_points.txt
yyperf-0.6.9.dist-info/pbr.json
yyperf-0.6.9.dist-info/top_level.txt
yyperf-0.6.9.dist-info/RECORD
