Metadata-Version: 2.1
Name: yyperf
Version: 0.6.9
Summary: tool for perfmonce
Home-page: https://github.com/mrx1203/
Author: mrx102
Author-email: mrx102@163.com
License: MIT
Platform: UNKNOWN
Classifier: Environment :: Console
Classifier: Intended Audience :: Developers
Classifier: Operating System :: OS Independent
Classifier: Programming Language :: Python
Requires-Python: >=3.6
Requires-Dist: tornado (>=4.3)
Requires-Dist: six
Requires-Dist: pillow
Requires-Dist: logzero
Requires-Dist: cached-property
Requires-Dist: psutil
Requires-Dist: requests
Requires-Dist: pynvml
Requires-Dist: wmi
Requires-Dist: uiautomator2 (>=2.10.1)
Requires-Dist: facebook-wda (>=1.0.5)
Requires-Dist: py-ios-device (==2.2.3.1)
Requires-Dist: tidevice (==0.6.8)
Requires-Dist: pynvml (==11.4.1)
Requires-Dist: pywin32 ; (sys_platform == 'win32')
